Workbook

Sheet 1. Cover
C4: MONARCH CONVICTION AMC
C5: Launchpad Alpha 2026 — Institutional Financial Model
C7: Date Generated: February 27, 2026
C10: MODEL STRUCTURE & INDEX
C12: 1. Cover: Model details and formatting legend
C13: 2. Dashboard: Visual summary of KPIs and breakeven metrics
C14: 3. Assumptions: Core drivers (AUM, Yield, Opex) - ALL INPUTS HERE
C15: 4. Base Case: Granular 5-Year Profit & Loss (Formula Driven)
C16: 5. Conservative: Sensitized 5-Year Profit & Loss (Formula Driven)
C19: FORMATTING LEGEND
C20: Hardcoded Inputs (Yellow fill, Blue text) - Modify these only
C21: Calculations (Black text) - Do not modify

Sheet 2. Assumptions
C2: KEY ASSUMPTIONS & DRIVERS
D4: Year 1 | E4: Year 2 | F4: Year 3 | G4: Year 4 | H4: Year 5
C5: 1. ASSETS UNDER MANAGEMENT (Rs. Crore)
C6: Base Case - MF AUM | D6: 700 | E6: 1200 | F6: 1800 | G6: 2600 | H6: 3800
C7: Base Case - SIF AUM | D7: 0 | E7: 300 | F7: 600 | G7: 1000 | H7: 1800
C9: Conservative Case - MF AUM | D9: 410 | E9: 800 | F9: 1300 | G9: 1900 | H9: 2800
C10: Conservative Case - SIF AUM | D10: 0 | E10: 150 | F10: 350 | G10: 600 | H10: 1000
C12: 2. YIELD ASSUMPTIONS
C13: Blended Net AMC Retention (MF & SIF) | D13: 0.0073 | E13: 0.0073 | F13: 0.0073 | G13: 0.0073 | H13: 0.0073
C15: 3. BASE CASE COST DRIVERS (Rs. Crore)
C16: Investment Team (incl SIF CIO) | D16: 10.5 | E16: 11 | F16: 11.5 | G16: 12 | H16: 12.5
C17: Operations & R&T (Variable) | D17: 1.5 | E17: 3 | F17: 4 | G17: 4.5 | H17: 5.5
C18: Technology (Portal & Dashboard) | D18: 2.5 | E18: 1.5 | F18: 1.5 | G18: 1.5 | H18: 1.5
C19: Content & Distribution (NFOs) | D19: 2.5 | E19: 3 | F19: 2.5 | G19: 2.5 | H19: 2.5
C20: Compliance & Legal | D20: 1 | E20: 1.5 | F20: 1.5 | G20: 1.5 | H20: 1.5
C21: Office & Overhead | D21: 0.5 | E21: 0.5 | F21: 0.5 | G21: 0.5 | H21: 0.5
C23: 4. CONSERVATIVE CASE COST DRIVERS (Rs. Crore)
C24: Investment Team (incl SIF CIO) | D24: 10.5 | E24: 10.5 | F24: 11 | G24: 11.5 | H24: 12
C25: Operations & R&T (Variable) | D25: 1 | E25: 2 | F25: 3 | G25: 4 | H25: 5
C26: Technology (Portal & Dashboard) | D26: 2.5 | E26: 1.5 | F26: 1.5 | G26: 1.5 | H26: 1.5
C27: Content & Distribution (NFOs) | D27: 2.5 | E27: 3.5 | F27: 3 | G27: 2.5 | H27: 2.5
C28: Compliance & Legal | D28: 1 | E28: 1.5 | F28: 1.5 | G28: 1.5 | H28: 1.5
C29: Office & Overhead | D29: 0.5 | E29: 0.5 | F29: 0.5 | G29: 0.5 | H29: 0.5
C31: 5. CORPORATE PARAMETERS
C32: Monarch Networth (Rs. Crore) | D32: 796

Sheet 3. Base Case
C2: BASE CASE — DETAILED P&L
D4: Year 1 | E4: Year 2 | F4: Year 3 | G4: Year 4 | H4: Year 5
C5: ASSETS UNDER MANAGEMENT (Rs. Crore)
C6: Mutual Fund (MF) AUM | D6: ='2. Assumptions'!D6 -> 0 | E6: ='2. Assumptions'!E6 -> 0 | F6: ='2. Assumptions'!F6 -> 0 | G6: ='2. Assumptions'!G6 -> 0 | H6: ='2. Assumptions'!H6 -> 0
C7: Specialized Investment Fund (SIF) AUM | D7: ='2. Assumptions'!D7 -> 0 | E7: ='2. Assumptions'!E7 -> 0 | F7: ='2. Assumptions'!F7 -> 0 | G7: ='2. Assumptions'!G7 -> 0 | H7: ='2. Assumptions'!H7 -> 0
C8: Total Period-End AUM | D8: =SUM(D6:D7) -> 0 | E8: =SUM(E6:E7) -> 0 | F8: =SUM(F6:F7) -> 0 | G8: =SUM(G6:G7) -> 0 | H8: =SUM(H6:H7) -> 0
C10: REVENUE (Rs. Crore)
C11: Blended Net AMC Retention Yield | D11: ='2. Assumptions'!D13 -> 0 | E11: ='2. Assumptions'!E13 -> 0 | F11: ='2. Assumptions'!F13 -> 0 | G11: ='2. Assumptions'!G13 -> 0 | H11: ='2. Assumptions'!H13 -> 0
C12: Management Fee Revenue | D12: =D8*D11 -> 0 | E12: =E8*E11 -> 0 | F12: =F8*F11 -> 0 | G12: =G8*G11 -> 0 | H12: =H8*H11 -> 0
C14: OPERATING EXPENSES (Rs. Crore)
C15: Investment Team (incl SIF CIO) | D15: ='2. Assumptions'!D16 -> 0 | E15: ='2. Assumptions'!E16 -> 0 | F15: ='2. Assumptions'!F16 -> 0 | G15: ='2. Assumptions'!G16 -> 0 | H15: ='2. Assumptions'!H16 -> 0
C16: Operations & R&T (Variable) | D16: ='2. Assumptions'!D17 -> 0 | E16: ='2. Assumptions'!E17 -> 0 | F16: ='2. Assumptions'!F17 -> 0 | G16: ='2. Assumptions'!G17 -> 0 | H16: ='2. Assumptions'!H17 -> 0
C17: Technology (Portal & Dashboard) | D17: ='2. Assumptions'!D18 -> 0 | E17: ='2. Assumptions'!E18 -> 0 | F17: ='2. Assumptions'!F18 -> 0 | G17: ='2. Assumptions'!G18 -> 0 | H17: ='2. Assumptions'!H18 -> 0
C18: Content & Distribution (NFOs) | D18: ='2. Assumptions'!D19 -> 0 | E18: ='2. Assumptions'!E19 -> 0 | F18: ='2. Assumptions'!F19 -> 0 | G18: ='2. Assumptions'!G19 -> 0 | H18: ='2. Assumptions'!H19 -> 0
C19: Compliance & Legal | D19: ='2. Assumptions'!D20 -> 0 | E19: ='2. Assumptions'!E20 -> 0 | F19: ='2. Assumptions'!F20 -> 0 | G19: ='2. Assumptions'!G20 -> 0 | H19: ='2. Assumptions'!H20 -> 0
C20: Office & Overhead | D20: ='2. Assumptions'!D21 -> 0 | E20: ='2. Assumptions'!E21 -> 0 | F20: ='2. Assumptions'!F21 -> 0 | G20: ='2. Assumptions'!G21 -> 0 | H20: ='2. Assumptions'!H21 -> 0
C21: Total Operating Expenses | D21: =SUM(D15:D20) -> 0 | E21: =SUM(E15:E20) -> 0 | F21: =SUM(F15:F20) -> 0 | G21: =SUM(G15:G20) -> 0 | H21: =SUM(H15:H20) -> 0
C23: PROFITABILITY METRICS
C24: Profit Before Tax (PBT) | D24: =D12-D21 -> 0 | E24: =E12-E21 -> 0 | F24: =F12-F21 -> 0 | G24: =G12-G21 -> 0 | H24: =H12-H21 -> 0
C25: PBT Margin (%) | D25: =IF(D24>0, D24/D12, "NM") -> 0 | E25: =IF(E24>0, E24/E12, "NM") -> 0 | F25: =IF(F24>0, F24/F12, "NM") -> 0 | G25: =IF(G24>0, G24/G12, "NM") -> 0 | H25: =IF(H24>0, H24/H12, "NM") -> 0
C27: CAPITAL DRAWDOWN ANALYSIS
C28: Cumulative Profit/Loss | D28: =MIN(0, D24) -> 0 | E28: =MIN(0, D28 + E24) -> 0 | F28: =MIN(0, E28 + F24) -> 0 | G28: =MIN(0, F28 + G24) -> 0 | H28: =MIN(0, G28 + H24) -> 0
C29: Monarch Networth | D29: ='2. Assumptions'!$D$32 -> 0 | E29: ='2. Assumptions'!$D$32 -> 0 | F29: ='2. Assumptions'!$D$32 -> 0 | G29: ='2. Assumptions'!$D$32 -> 0 | H29: ='2. Assumptions'!$D$32 -> 0
C30: Max Drawdown as % of Networth | D30: =D28 / D29 -> 0 | E30: =E28 / E29 -> 0 | F30: =F28 / F29 -> 0 | G30: =G28 / G29 -> 0 | H30: =H28 / H29 -> 0

Sheet 4. Conservative
C2: CONSERVATIVE CASE — DETAILED P&L
D4: Year 1 | E4: Year 2 | F4: Year 3 | G4: Year 4 | H4: Year 5
C5: ASSETS UNDER MANAGEMENT (Rs. Crore)
C6: Mutual Fund (MF) AUM | D6: ='2. Assumptions'!D9 -> 0 | E6: ='2. Assumptions'!E9 -> 0 | F6: ='2. Assumptions'!F9 -> 0 | G6: ='2. Assumptions'!G9 -> 0 | H6: ='2. Assumptions'!H9 -> 0
C7: Specialized Investment Fund (SIF) AUM | D7: ='2. Assumptions'!D10 -> 0 | E7: ='2. Assumptions'!E10 -> 0 | F7: ='2. Assumptions'!F10 -> 0 | G7: ='2. Assumptions'!G10 -> 0 | H7: ='2. Assumptions'!H10 -> 0
C8: Total Period-End AUM | D8: =SUM(D6:D7) -> 0 | E8: =SUM(E6:E7) -> 0 | F8: =SUM(F6:F7) -> 0 | G8: =SUM(G6:G7) -> 0 | H8: =SUM(H6:H7) -> 0
C10: REVENUE (Rs. Crore)
C11: Blended Net AMC Retention Yield | D11: ='2. Assumptions'!D13 -> 0 | E11: ='2. Assumptions'!E13 -> 0 | F11: ='2. Assumptions'!F13 -> 0 | G11: ='2. Assumptions'!G13 -> 0 | H11: ='2. Assumptions'!H13 -> 0
C12: Management Fee Revenue | D12: =D8*D11 -> 0 | E12: =E8*E11 -> 0 | F12: =F8*F11 -> 0 | G12: =G8*G11 -> 0 | H12: =H8*H11 -> 0
C14: OPERATING EXPENSES (Rs. Crore)
C15: Investment Team (incl SIF CIO) | D15: ='2. Assumptions'!D24 -> 0 | E15: ='2. Assumptions'!E24 -> 0 | F15: ='2. Assumptions'!F24 -> 0 | G15: ='2. Assumptions'!G24 -> 0 | H15: ='2. Assumptions'!H24 -> 0
C16: Operations & R&T (Variable) | D16: ='2. Assumptions'!D25 -> 0 | E16: ='2. Assumptions'!E25 -> 0 | F16: ='2. Assumptions'!F25 -> 0 | G16: ='2. Assumptions'!G25 -> 0 | H16: ='2. Assumptions'!H25 -> 0
C17: Technology (Portal & Dashboard) | D17: ='2. Assumptions'!D26 -> 0 | E17: ='2. Assumptions'!E26 -> 0 | F17: ='2. Assumptions'!F26 -> 0 | G17: ='2. Assumptions'!G26 -> 0 | H17: ='2. Assumptions'!H26 -> 0
C18: Content & Distribution (NFOs) | D18: ='2. Assumptions'!D27 -> 0 | E18: ='2. Assumptions'!E27 -> 0 | F18: ='2. Assumptions'!F27 -> 0 | G18: ='2. Assumptions'!G27 -> 0 | H18: ='2. Assumptions'!H27 -> 0
C19: Compliance & Legal | D19: ='2. Assumptions'!D28 -> 0 | E19: ='2. Assumptions'!E28 -> 0 | F19: ='2. Assumptions'!F28 -> 0 | G19: ='2. Assumptions'!G28 -> 0 | H19: ='2. Assumptions'!H28 -> 0
C20: Office & Overhead | D20: ='2. Assumptions'!D29 -> 0 | E20: ='2. Assumptions'!E29 -> 0 | F20: ='2. Assumptions'!F29 -> 0 | G20: ='2. Assumptions'!G29 -> 0 | H20: ='2. Assumptions'!H29 -> 0
C21: Total Operating Expenses | D21: =SUM(D15:D20) -> 0 | E21: =SUM(E15:E20) -> 0 | F21: =SUM(F15:F20) -> 0 | G21: =SUM(G15:G20) -> 0 | H21: =SUM(H15:H20) -> 0
C23: PROFITABILITY METRICS
C24: Profit Before Tax (PBT) | D24: =D12-D21 -> 0 | E24: =E12-E21 -> 0 | F24: =F12-F21 -> 0 | G24: =G12-G21 -> 0 | H24: =H12-H21 -> 0
C25: PBT Margin (%) | D25: =IF(D24>0, D24/D12, "NM") -> 0 | E25: =IF(E24>0, E24/E12, "NM") -> 0 | F25: =IF(F24>0, F24/F12, "NM") -> 0 | G25: =IF(G24>0, G24/G12, "NM") -> 0 | H25: =IF(H24>0, H24/H12, "NM") -> 0
C27: CAPITAL DRAWDOWN ANALYSIS
C28: Cumulative Profit/Loss | D28: =MIN(0, D24) -> 0 | E28: =MIN(0, D28 + E24) -> 0 | F28: =MIN(0, E28 + F24) -> 0 | G28: =MIN(0, F28 + G24) -> 0 | H28: =MIN(0, G28 + H24) -> 0
C29: Monarch Networth | D29: ='2. Assumptions'!$D$32 -> 0 | E29: ='2. Assumptions'!$D$32 -> 0 | F29: ='2. Assumptions'!$D$32 -> 0 | G29: ='2. Assumptions'!$D$32 -> 0 | H29: ='2. Assumptions'!$D$32 -> 0
C30: Max Drawdown as % of Networth | D30: =D28 / D29 -> 0 | E30: =E28 / E29 -> 0 | F30: =F28 / F29 -> 0 | G30: =G28 / G29 -> 0 | H30: =H28 / H29 -> 0

Sheet 5. Dashboard
C2: EXECUTIVE DASHBOARD
D4: Year 1 | E4: Year 2 | F4: Year 3 | G4: Year 4 | H4: Year 5
C5: Base Case AUM (Rs. Cr) | D5: ='3. Base Case'!D8 -> 0 | E5: ='3. Base Case'!E8 -> 0 | F5: ='3. Base Case'!F8 -> 0 | G5: ='3. Base Case'!G8 -> 0 | H5: ='3. Base Case'!H8 -> 0
C6: Base Case PBT (Rs. Cr) | D6: ='3. Base Case'!D18 -> 0 | E6: ='3. Base Case'!E18 -> 0 | F6: ='3. Base Case'!F18 -> 0 | G6: ='3. Base Case'!G18 -> 0 | H6: ='3. Base Case'!H18 -> 0
C7: Conservative PBT (Rs. Cr) | D7: ='4. Conservative'!D18 -> 0 | E7: ='4. Conservative'!E18 -> 0 | F7: ='4. Conservative'!F18 -> 0 | G7: ='4. Conservative'!G18 -> 0 | H7: ='4. Conservative'!H18 -> 0
